<idea-plugin>
    <extensions defaultExtensionNs="com.intellij">

        <!-- Bean System  -->
        <localInspection language="XML" enabledByDefault="true" groupPath="hybris" groupName="[y] Bean System"
                         bundle="i18n.HybrisBundle" key="hybris.inspections.system.bean.DuplicateBeanDefinition.key"
                         shortName="DuplicateBeanDefinition" level="WEAK WARNING"
                         implementationClass="com.intellij.idea.plugin.hybris.system.bean.inspections.rules.DuplicateBeanDefinition"/>
        <localInspection language="XML" enabledByDefault="true" groupPath="hybris" groupName="[y] Bean System"
                         bundle="i18n.HybrisBundle" key="hybris.inspections.system.bean.DuplicateEnumDefinition.key"
                         shortName="DuplicateEnumDefinition" level="WEAK WARNING"
                         implementationClass="com.intellij.idea.plugin.hybris.system.bean.inspections.rules.DuplicateEnumDefinition"/>
        <localInspection language="XML" enabledByDefault="true" groupPath="hybris" groupName="[y] Bean System"
                         bundle="i18n.HybrisBundle" key="hybris.inspections.system.bean.DuplicateBeanPropertyDefinition.key"
                         shortName="DuplicateBeanPropertyDefinition" level="ERROR"
                         implementationClass="com.intellij.idea.plugin.hybris.system.bean.inspections.rules.DuplicateBeanPropertyDefinition"/>
        <localInspection language="XML" enabledByDefault="true" groupPath="hybris" groupName="[y] Bean System"
                         bundle="i18n.HybrisBundle" key="hybris.inspections.system.bean.DuplicateEnumValueDefinition.key"
                         shortName="DuplicateEnumValueDefinition" level="ERROR"
                         implementationClass="com.intellij.idea.plugin.hybris.system.bean.inspections.rules.DuplicateEnumValueDefinition"/>

        <!-- Type System  -->
        <!-- Weak Warnings -->
        <localInspection language="XML" enabledByDefault="true" groupPath="hybris" groupName="[y] Type System"
                         bundle="i18n.HybrisBundle" key="hybris.inspections.system.type.MandatoryFieldMustHaveInitialValue.key"
                         shortName="MandatoryFieldMustHaveInitialValue" level="WEAK WARNING"
                         implementationClass="com.intellij.idea.plugin.hybris.type.system.inspections.rules.MandatoryFieldMustHaveInitialValue"/>

        <localInspection language="XML" enabledByDefault="true" groupPath="hybris" groupName="[y] Type System"
                         bundle="i18n.HybrisBundle" key="hybris.inspections.system.type.ImmutableFieldMustHaveInitialValue.key"
                         shortName="ImmutableFieldMustHaveInitialValue" level="WEAK WARNING"
                         implementationClass="com.intellij.idea.plugin.hybris.type.system.inspections.rules.ImmutableFieldMustHaveInitialValue"/>

        <localInspection language="XML" enabledByDefault="true" groupPath="hybris" groupName="[y] Type System"
                         bundle="i18n.HybrisBundle" key="hybris.inspections.system.type.TypeNameMustStartWithUppercaseLetter.key"
                         shortName="TypeNameMustStartWithUppercaseLetter" level="WEAK WARNING"
                         implementationClass="com.intellij.idea.plugin.hybris.type.system.inspections.rules.TypeNameMustStartWithUppercaseLetter"/>

        <localInspection language="XML" enabledByDefault="true" groupPath="hybris" groupName="[y] Type System"
                         bundle="i18n.HybrisBundle" key="hybris.inspections.system.type.QualifierMustStartWithLowercaseLetter.key"
                         shortName="QualifierMustStartWithLowercaseLetter" level="WEAK WARNING"
                         implementationClass="com.intellij.idea.plugin.hybris.type.system.inspections.rules.QualifierMustStartWithLowercaseLetter"/>

        <localInspection language="XML" enabledByDefault="true" groupPath="hybris" groupName="[y] Type System"
                         bundle="i18n.HybrisBundle" key="hybris.inspections.system.type.OrderingOfRelationShouldBeAvoided.key"
                         shortName="OrderingOfRelationShouldBeAvoided" level="WEAK WARNING"
                         implementationClass="com.intellij.idea.plugin.hybris.type.system.inspections.rules.OrderingOfRelationShouldBeAvoided"/>

        <localInspection language="XML" enabledByDefault="true" groupPath="hybris" groupName="[y] Type System"
                         bundle="i18n.HybrisBundle" key="hybris.inspections.system.type.ListsInRelationShouldBeAvoided.key"
                         shortName="ListsInRelationShouldBeAvoided" level="WEAK WARNING"
                         implementationClass="com.intellij.idea.plugin.hybris.type.system.inspections.rules.ListsInRelationShouldBeAvoided"/>

        <localInspection language="XML" enabledByDefault="true" groupPath="hybris" groupName="[y] Type System"
                         bundle="i18n.HybrisBundle"
                         key="hybris.inspections.system.type.UseOfUnoptimizedAttributesIsNotRecommended.key"
                         shortName="UseOfUnoptimizedAttributesIsNotRecommended" level="WEAK WARNING"
                         implementationClass="com.intellij.idea.plugin.hybris.type.system.inspections.rules.UseOfUnoptimizedAttributesIsNotRecommended"/>

        <localInspection language="XML" enabledByDefault="true" groupPath="hybris" groupName="[y] Type System"
                         bundle="i18n.HybrisBundle" key="hybris.inspections.system.type.CollectionsAreOnlyForDynamicAndJalo.key"
                         shortName="CollectionsAreOnlyForDynamicAndJalo" level="WEAK WARNING"
                         implementationClass="com.intellij.idea.plugin.hybris.type.system.inspections.rules.CollectionsAreOnlyForDynamicAndJalo"/>

        <localInspection language="XML" enabledByDefault="true" groupPath="hybris" groupName="[y] Type System"
                         bundle="i18n.HybrisBundle" key="hybris.inspections.system.type.TypeNameMustNotStartWithGenerated.key"
                         shortName="TypeNameMustNotStartWithGenerated" level="WEAK WARNING"
                         implementationClass="com.intellij.idea.plugin.hybris.type.system.inspections.rules.TypeNameMustNotStartWithGenerated"/>

        <localInspection language="XML" enabledByDefault="true" groupPath="hybris" groupName="[y] Type System"
                         bundle="i18n.HybrisBundle" key="hybris.inspections.system.type.TypeNameMustPointToExistingType.key"
                         shortName="TypeNameMustPointToExistingType" level="ERROR"
                         implementationClass="com.intellij.idea.plugin.hybris.type.system.inspections.rules.TypeNameMustPointToExistingType"/>

        <localInspection language="XML" enabledByDefault="true" groupPath="hybris" groupName="[y] Type System"
                         bundle="i18n.HybrisBundle" key="hybris.inspections.system.type.BooleanFieldCannotBeOptional.key"
                         shortName="BooleanFieldCannotBeOptional" level="WARNING"
                         implementationClass="com.intellij.idea.plugin.hybris.type.system.inspections.rules.BooleanFieldCannotBeOptional"/>

        <localInspection language="XML" enabledByDefault="true" groupPath="hybris" groupName="[y] Type System"
                         bundle="i18n.HybrisBundle" key="hybris.inspections.system.type.JaloPersistanceTypeIsDeprecated.key"
                         shortName="JaloPersistanceTypeIsDeprecated" level="WARNING"
                         implementationClass="com.intellij.idea.plugin.hybris.type.system.inspections.rules.JaloPersistanceTypeIsDeprecated"/>

        <localInspection language="XML" enabledByDefault="true" groupPath="hybris" groupName="[y] Type System"
                         bundle="i18n.HybrisBundle" key="hybris.inspections.system.type.CmpPersistanceTypeIsDeprecated.key"
                         shortName="CmpPersistanceTypeIsDeprecated" level="WARNING"
                         implementationClass="com.intellij.idea.plugin.hybris.type.system.inspections.rules.CmpPersistanceTypeIsDeprecated"/>

        <localInspection language="XML" enabledByDefault="true" groupPath="hybris" groupName="[y] Type System"
                         bundle="i18n.HybrisBundle"
                         key="hybris.inspections.system.type.DeploymentTableMustExistForItemExtendingGenericItem.key"
                         shortName="DeploymentTableMustExistForItemExtendingGenericItem" level="ERROR"
                         implementationClass="com.intellij.idea.plugin.hybris.type.system.inspections.rules.DeploymentTableMustExistForItemExtendingGenericItem"/>

        <localInspection language="XML" enabledByDefault="true" groupPath="hybris" groupName="[y] Type System"
                         bundle="i18n.HybrisBundle"
                         key="hybris.inspections.system.type.DeploymentTableMustNotBeRedeclaredInChildTypes.key"
                         shortName="DeploymentTableMustNotBeRedeclaredInChildTypes" level="ERROR"
                         implementationClass="com.intellij.idea.plugin.hybris.type.system.inspections.rules.DeploymentTableMustNotBeRedeclaredInChildTypes"/>

        <localInspection language="XML" enabledByDefault="true" groupPath="hybris" groupName="[y] Type System"
                         bundle="i18n.HybrisBundle"
                         key="hybris.inspections.system.type.DeploymentTypeCodeMustBeUnique.key"
                         shortName="DeploymentTypeCodeMustBeUnique" level="ERROR"
                         implementationClass="com.intellij.idea.plugin.hybris.type.system.inspections.rules.DeploymentTypeCodeMustBeUnique"/>

        <localInspection language="XML" enabledByDefault="true" groupPath="hybris" groupName="[y] Type System"
                         bundle="i18n.HybrisBundle"
                         key="hybris.inspections.system.type.DeploymentTableMustBeUnique.key"
                         shortName="DeploymentTableMustBeUnique" level="ERROR"
                         implementationClass="com.intellij.idea.plugin.hybris.type.system.inspections.rules.DeploymentTableMustBeUnique"/>

        <localInspection language="XML" enabledByDefault="true" groupPath="hybris" groupName="[y] Type System"
                         bundle="i18n.HybrisBundle"
                         key="hybris.inspections.system.type.JaloClassIsNotAllowedWhenAddingFieldsToExistingClass.key"
                         shortName="JaloClassIsNotAllowedWhenAddingFieldsToExistingClass" level="ERROR"
                         implementationClass="com.intellij.idea.plugin.hybris.type.system.inspections.rules.JaloClassIsNotAllowedWhenAddingFieldsToExistingClass"/>

        <localInspection language="XML" enabledByDefault="true" groupPath="hybris" groupName="[y] Type System"
                         bundle="i18n.HybrisBundle"
                         key="hybris.inspections.system.type.AttributeHandlerMustBeSetForDynamicAttribute.key"
                         shortName="AttributeHandlerMustBeSetForDynamicAttribute" level="ERROR"
                         implementationClass="com.intellij.idea.plugin.hybris.type.system.inspections.rules.AttributeHandlerMustBeSetForDynamicAttribute"/>

        <localInspection language="XML" enabledByDefault="true" groupPath="hybris" groupName="[y] Type System"
                         bundle="i18n.HybrisBundle"
                         key="hybris.inspections.system.type.DeploymentTypeCodeMustBeGreaterThanTenThousand.key"
                         shortName="DeploymentTypeCodeMustBeGreaterThanTenThousand" level="ERROR"
                         implementationClass="com.intellij.idea.plugin.hybris.type.system.inspections.rules.DeploymentTypeCodeMustBeGreaterThanTenThousand"/>

        <localInspection language="XML" enabledByDefault="true" groupPath="hybris" groupName="[y] Type System"
                         bundle="i18n.HybrisBundle"
                         key="hybris.inspections.system.type.DeploymentTableMustExistForManyToManyRelation.key"
                         shortName="DeploymentTableMustExistForManyToManyRelation" level="ERROR"
                         implementationClass="com.intellij.idea.plugin.hybris.type.system.inspections.rules.DeploymentTableMustExistForManyToManyRelation"/>

        <localInspection language="XML" enabledByDefault="true" groupPath="hybris" groupName="[y] Type System"
                         bundle="i18n.HybrisBundle"
                         key="hybris.inspections.system.type.DeploymentTypeCodeMustBeGreaterThanTenThousandForRelations.key"
                         shortName="DeploymentTypeCodesMustBeGreaterThanTenThousandForRelations" level="ERROR"
                         implementationClass="com.intellij.idea.plugin.hybris.type.system.inspections.rules.DeploymentTypeCodesMustBeGreaterThanTenThousandForRelations"/>

        <localInspection language="XML" enabledByDefault="true" groupPath="hybris" groupName="[y] Type System"
                         bundle="i18n.HybrisBundle" key="hybris.inspections.system.type.DeploymentTypeCodeReservedForCommonsExtension.key"
                         shortName="DeploymentTypeCodeReservedForCommonsExtension" level="ERROR"
                         implementationClass="com.intellij.idea.plugin.hybris.type.system.inspections.rules.DeploymentTypeCodeReservedForCommonsExtension"/>

        <localInspection language="XML" enabledByDefault="true" groupPath="hybris" groupName="[y] Type System"
                         bundle="i18n.HybrisBundle" key="hybris.inspections.system.type.DeploymentTypeCodeReservedForPrintExtension.key"
                         shortName="DeploymentTypeCodeReservedForPrintExtension" level="ERROR"
                         implementationClass="com.intellij.idea.plugin.hybris.type.system.inspections.rules.DeploymentTypeCodeReservedForPrintExtension"/>

        <localInspection language="XML" enabledByDefault="true" groupPath="hybris" groupName="[y] Type System"
                         bundle="i18n.HybrisBundle" key="hybris.inspections.system.type.DeploymentTypeCodeReservedForProcessingExtension.key"
                         shortName="DeploymentTypeCodeReservedForProcessingExtension" level="ERROR"
                         implementationClass="com.intellij.idea.plugin.hybris.type.system.inspections.rules.DeploymentTypeCodeReservedForProcessingExtension"/>

        <localInspection language="XML" enabledByDefault="true" groupPath="hybris" groupName="[y] Type System"
                         bundle="i18n.HybrisBundle"
                         key="hybris.inspections.system.type.DeploymentTypeCodeReservedForLegacyXPrintExtension.key"
                         shortName="DeploymentTypeCodeReservedForLegacyXPrintExtension" level="ERROR"
                         implementationClass="com.intellij.idea.plugin.hybris.type.system.inspections.rules.DeploymentTypeCodeReservedForLegacyXPrintExtension"/>

        <localInspection language="XML" enabledByDefault="true" groupPath="hybris" groupName="[y] Type System"
                         bundle="i18n.HybrisBundle" key="hybris.inspections.system.type.DeploymentTypeCodeReservedForB2BCommerceExtension.key"
                         shortName="DeploymentTypeCodeReservedForB2BCommerceExtension" level="ERROR"
                         implementationClass="com.intellij.idea.plugin.hybris.type.system.inspections.rules.DeploymentTypeCodeReservedForB2BCommerceExtension"/>

<!--        <localInspection language="XML" enabledByDefault="true" groupPath="hybris" groupName="[y] Type System"-->
<!--                         bundle="i18n.HybrisBundle" key="hybris.inspections.typesystem.CatalogAwareTypesMustHaveSpecificConditions.key"-->
<!--                         shortName="CatalogAwareTypesMustHaveSpecificConditions" level="ERROR"-->
<!--                         implementationClass="com.intellij.idea.plugin.hybris.type.system.inspections.rules.CatalogAwareTypesMustHaveSpecificConditions"/>-->

        <localInspection language="XML" enabledByDefault="true" groupPath="hybris" groupName="[y] Type System"
                         bundle="i18n.HybrisBundle" key="hybris.inspections.system.type.CatalogAwareUniqueKeyAttributeQualifier.key"
                         shortName="CatalogAwareUniqueKeyAttributeQualifier" level="ERROR"
                         implementationClass="com.intellij.idea.plugin.hybris.type.system.inspections.rules.CatalogAwareUniqueKeyAttributeQualifier"/>

        <localInspection language="XML" enabledByDefault="true" groupPath="hybris" groupName="[y] Type System"
                         bundle="i18n.HybrisBundle" key="hybris.inspections.system.type.CatalogAwareCatalogVersionAttributeQualifier.key"
                         shortName="CatalogAwareCatalogVersionAttributeQualifier" level="ERROR"
                         implementationClass="com.intellij.idea.plugin.hybris.type.system.inspections.rules.CatalogAwareCatalogVersionAttributeQualifier"/>

        <localInspection language="XML" enabledByDefault="true" groupPath="hybris" groupName="[y] Type System"
                         bundle="i18n.HybrisBundle" key="hybris.inspections.system.type.DefaultValueForEnumTypeMustBeAssignable.key"
                         shortName="DefaultValueForEnumTypeMustBeAssignable" level="ERROR"
                         implementationClass="com.intellij.idea.plugin.hybris.type.system.inspections.rules.DefaultValueForEnumTypeMustBeAssignable"/>

    </extensions>

</idea-plugin>